asyncgur/__init__.py
asyncgur/pygur.py
asyncgur-0.2.dist-info/LICENSE
asyncgur-0.2.dist-info/METADATA
asyncgur-0.2.dist-info/WHEEL
asyncgur-0.2.dist-info/top_level.txt
asyncgur-0.2.dist-info/RECORD
