Metadata-Version: 2.1
Name: asyncgur
Version: 0.2
Summary: UNKNOWN
Home-page: https://github.com/dyleee/asyncgur
Author: Dylee
Author-email: oyinxdoubx@gmail.com
License: MIT License
Platform: UNKNOWN
Classifier: Programming Language :: Python :: 3
Classifier: License :: OSI Approved :: MIT License
Classifier: Operating System :: OS Independent
Requires-Python: >=3.6
Requires-Dist: aiohttp
Requires-Dist: dacite
